cinemol/__init__.py
cinemol/__main__.py
cinemol/api.py
cinemol/cli.py
cinemol/fitting.py
cinemol/geometry.py
cinemol/model.py
cinemol/parsers.py
cinemol/py.typed
cinemol/style.py
cinemol/svg.py
cinemol/version.py
cinemol-1.0.2.dist-info/LICENSE
cinemol-1.0.2.dist-info/METADATA
cinemol-1.0.2.dist-info/WHEEL
cinemol-1.0.2.dist-info/entry_points.txt
cinemol-1.0.2.dist-info/top_level.txt
cinemol-1.0.2.dist-info/RECORD
