Metadata-Version: 2.2
Name: cinemol
Version: 1.0.2
Summary: CineMol is a tool for drawing small molecule configurations directly to SVG.
Home-page: https://github.com/moltools/CineMol
Download-URL: https://github.com/moltools/CineMol/releases
Author: David Meijer
Author-email: david.meijer@wur.nl
Maintainer: David Meijer
Maintainer-email: david.meijer@wur.nl
License: MIT
Project-URL: Tracker, https://github.com/moltools/CineMol/issues
Project-URL: Source, https://github.com/moltools/CineMol
Project-URL: Documentation, https://cinemol.readthedocs.io
Keywords: snekpack,cookiecutter,scalable vector graphics,three-dimensional structure,molecular drawing,visualization
Classifier: Development Status :: 1 - Planning
Classifier: Environment :: Console
Classifier: Intended Audience :: Developers
Classifier: License :: OSI Approved :: MIT License
Classifier: Operating System :: OS Independent
Classifier: Framework :: Pytest
Classifier: Framework :: tox
Classifier: Framework :: Sphinx
Classifier: Programming Language :: Python
Classifier: Programming Language :: Python :: 3.10
Classifier: Programming Language :: Python :: 3.11
Classifier: Programming Language :: Python :: 3.12
Classifier: Programming Language :: Python :: 3 :: Only
Requires-Python: >=3.8
License-File: LICENSE
Requires-Dist: more_itertools
Requires-Dist: tqdm
Requires-Dist: click
Requires-Dist: more_click
Provides-Extra: tests
Requires-Dist: pytest; extra == "tests"
Requires-Dist: coverage; extra == "tests"
Provides-Extra: docs
Requires-Dist: sphinx; extra == "docs"
Requires-Dist: sphinx-rtd-theme; extra == "docs"
Requires-Dist: sphinx-click; extra == "docs"
Requires-Dist: sphinx_automodapi; extra == "docs"
Requires-Dist: autodoc_pydantic; extra == "docs"
Requires-Dist: texext; extra == "docs"
Dynamic: download-url
